{"assets":[{"id":"image_0","w":1920,"h":272,"u":"images/","p":"img_0.png"},{"id":"image_1","w":1920,"h":1080,"u":"images/","p":"img_1.png"},{"id":"image_2","w":640,"h":640,"u":"images/","p":"img_2.png"},{"id":"comp_84","layers":[{"ddd":0,"ind":0,"ty":4,"nm":"Primary Solid","ks":{"o":{"k":100},"r":{"k":0},"p":{"k":[960,540,0]},"a":{"k":[0,0,0]},"s":{"k":[100,100,100]}},"ao":0,"shapes":[{"ty":"gr","it":[{"ty":"rc","d":1,"s":{"k":[3194.406,2608.625]},"p":{"k":[0,0]},"r":{"k":0},"nm":"Rectangle Path 1"},{"ty":"fl","fillEnabled":true,"c":{"k":[0,0,0,1],"x":"var $bm_rt;\n$bm_rt = comp('Colors').layer('Main').content('Rectangle 1').content('Fill 1').color;"},"o":{"k":100},"nm":"Fill 1"},{"ty":"tr","p":{"k":[-114.797,-3.688],"ix":2},"a":{"k":[0,0],"ix":1},"s":{"k":[100,100],"ix":3},"r":{"k":0,"ix":6},"o":{"k":100,"ix":7},"sk":{"k":0,"ix":4},"sa":{"k":0,"ix":5},"nm":"Transform"}],"nm":"Rectangle 1"}],"ip":0,"op":300.00001221925,"st":0,"bm":0,"sr":1}]},{"id":"comp_85","layers":[{"ddd":0,"ind":0,"ty":0,"nm":"Highlight","td":1,"refId":"comp_86","ks":{"o":{"k":100},"r":{"k":0},"p":{"k":[110,144,0]},"a":{"k":[3.243,540,0]},"s":{"k":[{"i":{"x":[0,0.667,0.667],"y":[1,0.667,0.667]},"o":{"x":[0.167,0.167,0.167],"y":[0.167,0.167,0.167]},"n":["0_1_0p167_0p167","0p667_0p667_0p167_0p167","0p667_0p667_0p167_0p167"],"t":7,"s":[0,8,100],"e":[30,8,100]},{"i":{"x":[0,0.667,0.667],"y":[0,0.667,0.667]},"o":{"x":[0.167,0.167,0.167],"y":[0.167,0.167,0.167]},"n":["0_0_0p167_0p167","0p667_0p667_0p167_0p167","0p667_0p667_0p167_0p167"],"t":20,"s":[30,8,100],"e":[30,8,100]},{"i":{"x":[0.833,0.833,0.833],"y":[0.833,0.833,0.833]},"o":{"x":[0.167,0.167,0.167],"y":[0,0.167,0.167]},"n":["0p833_0p833_0p167_0","0p833_0p833_0p167_0p167","0p833_0p833_0p167_0p167"],"t":130,"s":[30,8,100],"e":[0,8,100]},{"t":143.000005824509}]}},"ao":0,"w":1920,"h":1080,"ip":-13.0000005295009,"op":166.000006761319,"st":-13.0000005295009,"bm":0,"sr":1},{"ddd":0,"ind":1,"ty":5,"nm":"User","tt":1,"ks":{"o":{"k":100},"r":{"k":0},"p":{"k":[150,154,0]},"a":{"k":[0,0,0]},"s":{"k":[100,100,100]}},"ao":0,"ef":[{"ty":20,"nm":"Tint","ix":1,"ef":[{"ty":2,"nm":"Map Black To","mn":"ADBE Tint-0001","ix":1,"v":{"k":[0,0,0,0],"x":"var $bm_rt;\n$bm_rt = comp('Colors').layer('Text').content('Rectangle 1').content('Fill 1').color;"}},{"ty":2,"nm":"Map White To","mn":"ADBE Tint-0002","ix":2,"v":{"k":[1,1,1,0],"x":"var $bm_rt;\n$bm_rt = effect('Tint')('Map Black To');"}},{"ty":0,"nm":"Amount to Tint","mn":"ADBE Tint-0003","ix":3,"v":{"k":100}},{"ty":6,"nm":"","mn":"ADBE Tint-0004","ix":4,"v":0},{"ty":7,"nm":"GPU Rendering","mn":"ADBE Force CPU GPU","ix":5,"v":{"k":1}}]}],"t":{"d":{"s":31,"f":"NotoSans-Bold","t":"@USER","j":0,"tr":0,"lh":37.2,"fc":[1,1,1]},"p":{},"m":{"g":1,"a":{"k":[0,0]}},"a":[]},"ip":-46.0000018736184,"op":180.00000733155,"st":0,"bm":0,"sr":1},{"ddd":0,"ind":2,"ty":0,"nm":"Highlight","refId":"comp_86","ks":{"o":{"k":100},"r":{"k":0},"p":{"k":[110,144,0]},"a":{"k":[3.243,540,0]},"s":{"k":[{"i":{"x":[0,0.667,0.667],"y":[1,0.667,0.667]},"o":{"x":[0.167,0.167,0.167],"y":[0.167,0.167,0.167]},"n":["0_1_0p167_0p167","0p667_0p667_0p167_0p167","0p667_0p667_0p167_0p167"],"t":7,"s":[0,8,100],"e":[30,8,100]},{"i":{"x":[0,0.667,0.667],"y":[0,0.667,0.667]},"o":{"x":[0.167,0.167,0.167],"y":[0.167,0.167,0.167]},"n":["0_0_0p167_0p167","0p667_0p667_0p167_0p167","0p667_0p667_0p167_0p167"],"t":20,"s":[30,8,100],"e":[30,8,100]},{"i":{"x":[0.833,0.833,0.833],"y":[0.833,0.833,0.833]},"o":{"x":[0.167,0.167,0.167],"y":[0,0.167,0.167]},"n":["0p833_0p833_0p167_0","0p833_0p833_0p167_0p167","0p833_0p833_0p167_0p167"],"t":130,"s":[30,8,100],"e":[0,8,100]},{"t":143.000005824509}]}},"ao":0,"w":1920,"h":1080,"ip":-13.0000005295009,"op":166.000006761319,"st":-13.0000005295009,"bm":8,"sr":1}]},{"id":"comp_86","layers":[{"ddd":0,"ind":0,"ty":4,"nm":"Highlight Solid","ks":{"o":{"k":100},"r":{"k":0},"p":{"k":[960,540,0]},"a":{"k":[0,0,0]},"s":{"k":[100,100,100]}},"ao":0,"shapes":[{"ty":"gr","it":[{"ty":"rc","d":1,"s":{"k":[3194.406,2608.625]},"p":{"k":[0,0]},"r":{"k":0},"nm":"Rectangle Path 1"},{"ty":"fl","fillEnabled":true,"c":{"k":[0,0,0,1],"x":"var $bm_rt;\n$bm_rt = comp('Colors').layer('Highlight').content('Rectangle 1').content('Fill 1').color;"},"o":{"k":100},"nm":"Fill 1"},{"ty":"tr","p":{"k":[-114.797,-3.688],"ix":2},"a":{"k":[0,0],"ix":1},"s":{"k":[100,100],"ix":3},"r":{"k":0,"ix":6},"o":{"k":100,"ix":7},"sk":{"k":0,"ix":4},"sa":{"k":0,"ix":5},"nm":"Transform"}],"nm":"Rectangle 1"}],"ip":0,"op":300.00001221925,"st":0,"bm":0,"sr":1}]},{"id":"comp_87","layers":[{"ddd":0,"ind":0,"ty":2,"nm":"Gradient_02.png","cl":"png","refId":"image_1","ks":{"o":{"k":100},"r":{"k":0},"p":{"k":[960,540,0]},"a":{"k":[960,540,0]},"s":{"k":[100,100,100]}},"ao":0,"ef":[{"ty":20,"nm":"Tint","ix":1,"ef":[{"ty":2,"nm":"Map Black To","mn":"ADBE Tint-0001","ix":1,"v":{"k":[0,0,0,0],"x":"var $bm_rt;\n$bm_rt = comp('Colors').layer('Secondary').content('Rectangle 1').content('Fill 1').color;"}},{"ty":2,"nm":"Map White To","mn":"ADBE Tint-0002","ix":2,"v":{"k":[1,1,1,0],"x":"var $bm_rt;\n$bm_rt = effect('Tint')('Map Black To');"}},{"ty":0,"nm":"Amount to Tint","mn":"ADBE Tint-0003","ix":3,"v":{"k":100}},{"ty":6,"nm":"","mn":"ADBE Tint-0004","ix":4,"v":0},{"ty":7,"nm":"GPU Rendering","mn":"ADBE Force CPU GPU","ix":5,"v":{"k":1}}]}],"ip":0,"op":817.000033277092,"st":0,"bm":0,"sr":1}]},{"id":"comp_88","layers":[{"ddd":0,"ind":0,"ty":4,"nm":"Secondary Solid","ks":{"o":{"k":100},"r":{"k":0},"p":{"k":[960,540,0]},"a":{"k":[0,0,0]},"s":{"k":[100,100,100]}},"ao":0,"shapes":[{"ty":"gr","it":[{"ty":"rc","d":1,"s":{"k":[3194.406,2608.625]},"p":{"k":[0,0]},"r":{"k":0},"nm":"Rectangle Path 1"},{"ty":"fl","fillEnabled":true,"c":{"k":[0,0,0,1],"x":"var $bm_rt;\n$bm_rt = comp('Colors').layer('Secondary').content('Rectangle 1').content('Fill 1').color;"},"o":{"k":100},"nm":"Fill 1"},{"ty":"tr","p":{"k":[-114.797,-3.688],"ix":2},"a":{"k":[0,0],"ix":1},"s":{"k":[100,100],"ix":3},"r":{"k":0,"ix":6},"o":{"k":100,"ix":7},"sk":{"k":0,"ix":4},"sa":{"k":0,"ix":5},"nm":"Transform"}],"nm":"Rectangle 1"}],"ip":0,"op":300.00001221925,"st":0,"bm":0,"sr":1}]},{"id":"comp_89","layers":[{"ddd":0,"ind":0,"ty":2,"nm":"Photo_01","refId":"image_2","ks":{"o":{"k":100},"r":{"k":0},"p":{"k":[960,540,0]},"a":{"k":[320,320,0]},"s":{"k":[{"i":{"x":[0.833,0.833,0.833],"y":[0.833,0.833,0.833]},"o":{"x":[0.167,0.167,0.167],"y":[0.167,0.167,0.167]},"n":["0p833_0p833_0p167_0p167","0p833_0p833_0p167_0p167","0p833_0p833_0p167_0p167"],"t":0,"s":[303,303,100],"e":[324,324,100]},{"t":601.000024479232}]}},"ao":0,"ip":0,"op":852.000034702671,"st":0,"bm":0,"sr":1}]}],"fonts":{"list":[{"fName":"NotoSans-Bold","fFamily":"NotoSans","fStyle":"Bold","ascent":71.009145507589},{"fName":"NotoSans","fFamily":"NotoSans","fStyle":"Regular","ascent":71.009145507589}]},"layers":[{"ddd":0,"ind":1,"ty":0,"nm":"Primary","refId":"comp_84","ks":{"o":{"k":100},"r":{"k":0},"p":{"k":[{"i":{"x":0.833,"y":0.833},"o":{"x":1,"y":0},"n":"0p833_0p833_1_0","t":132,"s":[3026,540,0],"e":[960,540,0],"to":[-344.333343505859,0,0],"ti":[344.333343505859,0,0]},{"t":149.000006068894}]},"a":{"k":[960,540,0]},"s":{"k":[100,100,100]}},"ao":0,"w":1920,"h":1080,"ip":117.000004765508,"op":417.000016984758,"st":117.000004765508,"bm":0,"sr":1},{"ddd":0,"ind":2,"ty":2,"nm":"gradient.png","cl":"png","parent":1,"refId":"image_0","ks":{"o":{"k":65},"r":{"k":-90},"p":{"k":[-28.231,540,0]},"a":{"k":[960,136,0]},"s":{"k":[100,46,100]}},"ao":0,"ip":118.000004806239,"op":268.000010915864,"st":118.000004806239,"bm":0,"sr":1},{"ddd":0,"ind":3,"ty":5,"nm":"Tweet","parent":10,"ks":{"o":{"k":100},"r":{"k":0},"p":{"k":[1104.155,507,0]},"a":{"k":[0,0,0]},"s":{"k":[100,100,100]}},"ao":0,"ef":[{"ty":20,"nm":"Tint","ix":1,"ef":[{"ty":2,"nm":"Map Black To","mn":"ADBE Tint-0001","ix":1,"v":{"k":[0,0,0,0],"x":"var $bm_rt;\n$bm_rt = comp('Colors').layer('Text').content('Rectangle 1').content('Fill 1').color;"}},{"ty":2,"nm":"Map White To","mn":"ADBE Tint-0002","ix":2,"v":{"k":[1,1,1,0],"x":"var $bm_rt;\n$bm_rt = effect('Tint')('Map Black To');"}},{"ty":0,"nm":"Amount to Tint","mn":"ADBE Tint-0003","ix":3,"v":{"k":100}},{"ty":6,"nm":"","mn":"ADBE Tint-0004","ix":4,"v":0},{"ty":7,"nm":"GPU Rendering","mn":"ADBE Force CPU GPU","ix":5,"v":{"k":1}}]}],"t":{"d":{"sz":[574,740],"ps":[-1034,-187],"mf":20,"s":53,"f":"NotoSans","t":"Idk why ppl feel like they have to combat #BlackLivesMatter w/ All Lives Matter. It bothers them so much that one movement isn't about them ","j":0,"tr":0,"lh":63.6000061035156,"fc":[0,0,0]},"p":{},"m":{"g":1,"a":{"k":[0,0]}},"a":[]},"ip":19.0000007738859,"op":226.000009205169,"st":41.0000016699642,"bm":0,"sr":1},{"ddd":0,"ind":4,"ty":0,"nm":"PhotoCredit_01","refId":"comp_85","ks":{"o":{"k":100},"r":{"k":0},"p":{"k":[348,996,0]},"a":{"k":[400,150,0]},"s":{"k":[100,100,100]}},"ao":0,"w":800,"h":300,"ip":13.0000005295009,"op":163.000006639126,"st":13.0000005295009,"bm":0,"sr":1},{"ddd":0,"ind":6,"ty":5,"nm":"User","parent":10,"ks":{"o":{"k":100},"r":{"k":0},"p":{"k":[78,256,0]},"a":{"k":[8,0,0]},"s":{"k":[100,100,100]}},"ao":0,"ef":[{"ty":20,"nm":"Tint","ix":1,"ef":[{"ty":2,"nm":"Map Black To","mn":"ADBE Tint-0001","ix":1,"v":{"k":[0,0,0,0],"x":"var $bm_rt;\n$bm_rt = comp('Colors').layer('Text').content('Rectangle 1').content('Fill 1').color;"}},{"ty":2,"nm":"Map White To","mn":"ADBE Tint-0002","ix":2,"v":{"k":[1,1,1,0],"x":"var $bm_rt;\n$bm_rt = effect('Tint')('Map Black To');"}},{"ty":0,"nm":"Amount to Tint","mn":"ADBE Tint-0003","ix":3,"v":{"k":100}},{"ty":6,"nm":"","mn":"ADBE Tint-0004","ix":4,"v":0},{"ty":7,"nm":"GPU Rendering","mn":"ADBE Force CPU GPU","ix":5,"v":{"k":1}}]}],"t":{"d":{"s":48,"f":"NotoSans-Bold","t":"@USER","j":0,"tr":0,"lh":57.6,"fc":[0,0,0]},"p":{},"m":{"g":1,"a":{"k":[0,0]}},"a":[]},"ip":19.0000007738859,"op":226.000009205169,"st":41.0000016699642,"bm":0,"sr":1},{"ddd":0,"ind":8,"ty":0,"nm":"Gradient_Secondary","parent":10,"refId":"comp_87","ks":{"o":{"k":100},"r":{"k":-90},"p":{"k":[-314,540,0]},"a":{"k":[960,540,0]},"s":{"k":[68,113,100]}},"ao":0,"w":1920,"h":1080,"ip":0,"op":600.000024438501,"st":0,"bm":0,"sr":1},{"ddd":0,"ind":9,"ty":0,"nm":"Secondary","parent":10,"refId":"comp_88","ks":{"o":{"k":100},"r":{"k":0},"p":{"k":[1250,540,0]},"a":{"k":[960,540,0]},"s":{"k":[100,100,100]}},"ao":0,"w":1920,"h":1080,"ip":0,"op":300.00001221925,"st":0,"bm":0,"sr":1},{"ddd":0,"ind":10,"ty":3,"nm":"Secondary","ks":{"o":{"k":0},"r":{"k":0},"p":{"k":[{"i":{"x":0.349,"y":1},"o":{"x":0.621,"y":0},"n":"0p349_1_0p621_0","t":12,"s":[3263,540,0],"e":[2154,540,0],"to":[-184.83332824707,0,0],"ti":[184.83332824707,0,0]},{"i":{"x":0.349,"y":0.349},"o":{"x":0.167,"y":0.167},"n":"0p349_0p349_0p167_0p167","t":31,"s":[2154,540,0],"e":[2154,540,0],"to":[0,0,0],"ti":[0,0,0]},{"i":{"x":0.833,"y":0.833},"o":{"x":1,"y":0},"n":"0p833_0p833_1_0","t":132,"s":[2154,540,0],"e":[939,540,0],"to":[-202.5,0,0],"ti":[202.5,0,0]},{"t":149.000006068894}]},"a":{"k":[960,540,0]},"s":{"k":[100,100,100]}},"ao":0,"ip":11.0000004480392,"op":311.00001266729,"st":11.0000004480392,"bm":0,"sr":1},{"ddd":0,"ind":11,"ty":0,"nm":"Primary","refId":"comp_84","ks":{"o":{"k":100},"r":{"k":0},"p":{"k":[{"i":{"x":0,"y":1},"o":{"x":0.167,"y":0.167},"n":"0_1_0p167_0p167","t":0,"s":[960,540,0],"e":[-45,540,0],"to":[-167.5,0,0],"ti":[167.5,0,0]},{"t":12.00000048877}]},"a":{"k":[960,540,0]},"s":{"k":[100,100,100]}},"ao":0,"w":1920,"h":1080,"ip":0,"op":12.00000048877,"st":0,"bm":0,"sr":1},{"ddd":0,"ind":12,"ty":2,"nm":"gradient.png","cl":"png","parent":11,"refId":"image_0","ks":{"o":{"k":100},"r":{"k":90},"p":{"k":[1983.782,540,0]},"a":{"k":[960,136,0]},"s":{"k":[100,53,100]}},"ao":0,"ip":0,"op":12.00000048877,"st":0,"bm":0,"sr":1},{"ddd":0,"ind":13,"ty":0,"nm":"Photo_01","refId":"comp_89","ks":{"o":{"k":100},"r":{"k":0},"p":{"k":[{"i":{"x":0,"y":1},"o":{"x":0.167,"y":0.167},"n":"0_1_0p167_0p167","t":0,"s":[960,540,0],"e":[1977,540,0],"to":[169.5,0,0],"ti":[48,0,0]},{"i":{"x":0.667,"y":1},"o":{"x":0.333,"y":0},"n":"0p667_1_0p333_0","t":12,"s":[1977,540,0],"e":[672,540,0],"to":[-48,0,0],"ti":[217.5,0,0]},{"t":27.0000010997325}]},"a":{"k":[960,540,0]},"s":{"k":[100,100,100]}},"ao":0,"w":1920,"h":1080,"ip":0,"op":600.000024438501,"st":0,"bm":0,"sr":1},{"ddd":0,"ind":14,"ty":2,"nm":"gradient.png","cl":"png","parent":13,"refId":"image_0","ks":{"o":{"k":47},"r":{"k":-90},"p":{"k":[-58,540,0]},"a":{"k":[960,136,0]},"s":{"k":[100,50,100]}},"ao":0,"ip":0,"op":150.000006109625,"st":0,"bm":0,"sr":1},{"ddd":0,"ind":15,"ty":0,"nm":"Primary","refId":"comp_84","ks":{"o":{"k":100},"r":{"k":0},"p":{"k":[{"i":{"x":0.833,"y":0.833},"o":{"x":1,"y":0},"n":"0p833_0p833_1_0","t":12,"s":[-45,540,0],"e":[960,540,0],"to":[167.5,0,0],"ti":[-167.5,0,0]},{"t":27.0000010997325}]},"a":{"k":[960,540,0]},"s":{"k":[100,100,100]}},"ao":0,"w":1920,"h":1080,"ip":12.00000048877,"op":34.0000013848484,"st":0,"bm":0,"sr":1},{"ddd":0,"ind":16,"ty":2,"nm":"gradient.png","cl":"png","parent":15,"refId":"image_0","ks":{"o":{"k":100},"r":{"k":90},"p":{"k":[1983.782,540,0]},"a":{"k":[960,136,0]},"s":{"k":[100,53,100]}},"ao":0,"ip":12.00000048877,"op":34.0000013848484,"st":0,"bm":0,"sr":1},{"ddd":0,"ind":17,"ty":0,"nm":"Primary","refId":"comp_84","ks":{"o":{"k":100},"r":{"k":0},"p":{"k":[960,540,0]},"a":{"k":[960,540,0]},"s":{"k":[100,100,100]}},"ao":0,"w":1920,"h":1080,"ip":0,"op":300.00001221925,"st":0,"bm":0,"sr":1},{"ddd":0,"ind":18,"ty":0,"nm":"Photo_01","refId":"comp_89","ks":{"o":{"k":100},"r":{"k":0},"p":{"k":[960,540,0]},"a":{"k":[960,540,0]},"s":{"k":[100,100,100]}},"ao":0,"w":1920,"h":1080,"ip":0,"op":600.000024438501,"st":0,"bm":0,"sr":1}],"v":"4.4.14","ddd":0,"ip":0,"op":150.000006109625,"fr":29.9700012207031,"w":1920,"h":1080,"chars":[]}